rsparam/__init__.py
rsparam/cli.py
rsparam/tests/__init__.py
rsparam/tests/clitests.sh
rsparam/tests/file1.txt
rsparam/tests/file2.txt
rsparam-0.1.15.dist-info/entry_points.txt
rsparam-0.1.15.dist-info/LICENSE
rsparam-0.1.15.dist-info/WHEEL
rsparam-0.1.15.dist-info/METADATA
rsparam-0.1.15.dist-info/RECORD
