Metadata-Version: 2.1
Name: rsparam
Version: 0.1.15
Summary: Utilities for working with Revit shared parameter files.
Home-page: https://github.com/eirannejad/rsparam
License: UNKNOWN
Author: Ehsan Iran-Nejad
Author-email: eirannejad@gmail.com
Classifier: License :: OSI Approved :: MIT License
Requires-Dist: docopt
Requires-Dist: colorful
Requires-Dist: tabulate
